pnp_timeit/__init__.py
pnp_timeit/pnp_timeit.py
pnp_timeit-0.5.0.dist-info/LICENSE
pnp_timeit-0.5.0.dist-info/METADATA
pnp_timeit-0.5.0.dist-info/WHEEL
pnp_timeit-0.5.0.dist-info/top_level.txt
pnp_timeit-0.5.0.dist-info/RECORD
