Metadata-Version: 2.1
Name: pnp-timeit
Version: 0.5.0
Summary: Measure execution time of small code snippets, write to log
Home-page: https://github.com/pypnp/pnp_timeit
Author: PyPnP
Author-email: pypnp@protonmail.com
License: UNKNOWN
Platform: UNKNOWN
Classifier: Programming Language :: Python :: 3
Classifier: License :: OSI Approved :: MIT License
Classifier: Operating System :: OS Independent
Requires-Python: >=3.6
